{"steam": [{"name": "PEAK", "link": "https://store.steampowered.com/app/3527290"}, {"name": "Stellaris", "link": "https://store.steampowered.com/app/281990"}, {"name": "Mage Arena", "link": "https://store.steampowered.com/app/3716600"}], "spotify": [{"name": "Blood Dye 40 by nano", "link": "https://open.spotify.com/track/7MmLTomo21EYBkQHpgUfr6"}, {"name": "Above the Neck by SOFIA ISELLA", "link": "https://open.spotify.com/track/5auAMRY9vhheFELgKicARA"}, {"name": "Pigstep (Stereo Mix) by Lena Raine", "link": "https://open.spotify.com/track/2TmUt0ofWMa02MdYkKhK4C"}], "kavita": [{"name": "Trafford's Trading Club", "link": "https://www.novelupdates.com/series/traffords-trading-club/", "summary": "Luo Qiu became the boss of a \u2018club\u2019 by chance.\n\nIt was a weird club that sold strange items and with servant girl that had 300 years of working experience. Countless people with dreams, hopes and ambitions came to the club to exchange anything precious they own for what they want. They would offer their lifespan, items, and even their soul. Every successful trade would increase Luo Qiu\u2019s lifespan by a little.\n\n\u201cTribute successful, your lifespan has increased by 99 years.\u201d\n\nAs thus, Luo Qiu began his endless life of the club\u2019s boss.", "completed": false, "completion_progress": 0.6560509554140127}]}